fqdn_parser/__init__.py
fqdn_parser/suffixes.py
fqdn_parser/tld_ranks.py
fqdn_parser/tld_reg_date_parser.py
fqdn_parser/tld_reg_dates_v1.txt
fqdn_parser/entropy/__init__.py
fqdn_parser/entropy/char_probabilities.py
fqdn_parser/entropy/domain_entropy.py
fqdn_parser/utils/__init__.py
fqdn_parser/utils/ascii_ify.py
fqdn_parser/utils/suffix_parser.py
fqdn_parser/utils/trie.py
fqdn_parser-2.1.6.dist-info/LICENSE.txt
fqdn_parser-2.1.6.dist-info/METADATA
fqdn_parser-2.1.6.dist-info/WHEEL
fqdn_parser-2.1.6.dist-info/top_level.txt
fqdn_parser-2.1.6.dist-info/RECORD
